tee/__init__.py
tee/__init__.pyi
tee/_version.py
tee/condition.py
tee/connection.py
tee/database.py
tee/delete.py
tee/errors.py
tee/executor.py
tee/fields.py
tee/insert.py
tee/model.py
tee/operation.py
tee/select.py
tee/statement.py
tee/update.py
tee/where.py
tee_orm-0.1.0.dist-info/licenses/LICENSE
tee_orm-0.1.0.dist-info/METADATA
tee_orm-0.1.0.dist-info/WHEEL
tee_orm-0.1.0.dist-info/top_level.txt
tee_orm-0.1.0.dist-info/RECORD
