Metadata-Version: 2.4
Name: tee-orm
Version: 0.1.0
Summary: 一个小巧的 Python ORM 框架，带有完整的类型系统支持
Home-page: https://github.com/tian-gua/tee
Author: tian-gua
Author-email: tian-gua <your-email@example.com>
Maintainer-email: tian-gua <your-email@example.com>
License-Expression: MIT
Project-URL: Homepage, https://github.com/tian-gua/tee
Project-URL: Documentation, https://github.com/tian-gua/tee#readme
Project-URL: Repository, https://github.com/tian-gua/tee
Project-URL: Bug Tracker, https://github.com/tian-gua/tee/issues
Keywords: orm,database,mysql,python,typing
Classifier: Development Status :: 3 - Alpha
Classifier: Intended Audience :: Developers
Classifier: Operating System :: OS Independent
Classifier: Programming Language :: Python :: 3
Classifier: Programming Language :: Python :: 3.8
Classifier: Programming Language :: Python :: 3.9
Classifier: Programming Language :: Python :: 3.10
Classifier: Programming Language :: Python :: 3.11
Classifier: Programming Language :: Python :: 3.12
Classifier: Topic :: Database
Classifier: Topic :: Software Development :: Libraries :: Python Modules
Classifier: Typing :: Typed
Requires-Python: >=3.8
License-File: LICENSE
Requires-Dist: PyMySQL>=1.0.0
Provides-Extra: dev
Requires-Dist: pytest>=7.0.0; extra == "dev"
Requires-Dist: pytest-cov>=4.0.0; extra == "dev"
Requires-Dist: black>=22.0.0; extra == "dev"
Requires-Dist: isort>=5.0.0; extra == "dev"
Requires-Dist: mypy>=1.0.0; extra == "dev"
Requires-Dist: flake8>=5.0.0; extra == "dev"
Dynamic: author
Dynamic: home-page
Dynamic: license-file
Dynamic: requires-python
